{
    "Ar36": {
        "error": 0.0004178386408788005,
        "error_type": "SEM",
        "filter_outliers_dict": {
            "filter_outliers": true,
            "iterations": 1,
            "std_devs": 2
        },
        "fit": "Parabolic",
        "fn": 323,
        "include_baseline_error": false,
        "n": 340,
        "reviewed": true,
        "value": 0.022218022866477262
    },
    "Ar37": {
        "error": 0.014108645648501845,
        "error_type": "SEM",
        "filter_outliers_dict": {
            "filter_outliers": true,
            "iterations": 1,
            "std_devs": 2
        },
        "fit": "Linear",
        "fn": 317,
        "include_baseline_error": false,
        "n": 340,
        "reviewed": true,
        "value": 14.567535546196478
    },
    "Ar38": {
        "error": 0.0053173664749294625,
        "error_type": "SEM",
        "filter_outliers_dict": {
            "filter_outliers": true,
            "iterations": 1,
            "std_devs": 2
        },
        "fit": "Linear",
        "fn": 322,
        "include_baseline_error": false,
        "n": 340,
        "reviewed": true,
        "value": -0.034756254356836935
    },
    "Ar39": {
        "error": 0.024944869448751298,
        "error_type": "SEM",
        "filter_outliers_dict": {
            "filter_outliers": true,
            "iterations": 1,
            "std_devs": 2
        },
        "fit": "Parabolic",
        "fn": 321,
        "include_baseline_error": false,
        "n": 340,
        "reviewed": true,
        "value": 2.664107682320539
    },
    "Ar40": {
        "error": 0.02446951819153217,
        "error_type": "SEM",
        "filter_outliers_dict": {
            "filter_outliers": true,
            "iterations": 1,
            "std_devs": 2
        },
        "fit": "Parabolic",
        "fn": 322,
        "include_baseline_error": false,
        "n": 340,
        "reviewed": true,
        "value": 17.728949660324872
    }
}